{
  "html": "<table border=\"1px\" style=\"width: 100%;\"> <tbody><tr><td>&nbsp;</td>\n\t\t\t\t\t<th>PC Number</th>\n\t\t\t\t\t<th>Date</th>\n\t\t\t\t\t<th>Chapter</th>\n\t\t\t\t\t<th>Bill</th>\n\t\t\t\t\t<th>Dept</th></tr><tr><td style=\"min-width: 120px;\">&nbsp;</td><td>1990-1663</td><td>1990-07-31</td><td>0</td><td></td><td>JUS,&nbsp; ,&nbsp; ,&nbsp; ,&nbsp; </td></tr><tr><td>Precis</td><td colspan=\"5\" id=\"precis\">Order fixing September 1, 1990, as the day upon which the Ontario Courts\nAmendment Act, 1989, being chapter 17 of the Statutes of Canada, 1990,\nshall COME INTO FORCE.\n</td></tr><tr><td>Registration</td><td colspan=\"5\" id=\"registration\"><strong>Registration: </strong>SI / 1990-0106  <strong>Publication Date:</strong> 1990-08-29</td></tr><tr><td>Attachments</td><td colspan=\"5\"></td></tr></tbody></table>",
  "pcNumber": "1990-1663",
  "htmlHash": "813f54d3b40386f5b77e79547b8ef80e",
  "attachments": [],
  "date": "1990-07-31",
  "chapter": "0",
  "bill": "",
  "department": "JUS, , , , ",
  "act": "",
  "subject": "",
  "precis": "Order fixing September 1, 1990, as the day upon which the Ontario Courts\nAmendment Act, 1989, being chapter 17 of the Statutes of Canada, 1990,\nshall COME INTO FORCE.\n",
  "registration": "Registration: SI / 1990-0106  Publication Date: 1990-08-29",
  "registration_type": "SI",
  "registration_id": "1990-0106",
  "registration_publication_date": "1990-08-29"
}