{
  "html": "<table border=\"1px\" style=\"width: 100%;\"> <tbody><tr><td>&nbsp;</td>\n\t\t\t\t\t<th>PC Number</th>\n\t\t\t\t\t<th>Date</th>\n\t\t\t\t\t<th>Chapter</th>\n\t\t\t\t\t<th>Bill</th>\n\t\t\t\t\t<th>Dept</th></tr><tr><td style=\"min-width: 120px;\">&nbsp;</td><td>1991-1571</td><td>1991-08-22</td><td>0</td><td></td><td>FIN,&nbsp; ,&nbsp; ,&nbsp; ,&nbsp; ,&nbsp; </td></tr><tr><td>Precis</td><td colspan=\"5\" id=\"precis\">Appointment of the Honourable Robert Carman Coates, of Amherst,\nNova Scotia, as a permanent member of the Canadian International Trade\nTribunal to hold office during good behaviour for a term of five years.\n</td></tr><tr><td>Attachments</td><td colspan=\"5\"></td></tr></tbody></table>",
  "pcNumber": "1991-1571",
  "htmlHash": "0f969ffe63e4811fd38f5c40cb34e71c",
  "attachments": [],
  "date": "1991-08-22",
  "chapter": "0",
  "bill": "",
  "department": "FIN, , , , , ",
  "act": "",
  "subject": "",
  "precis": "Appointment of the Honourable Robert Carman Coates, of Amherst,\nNova Scotia, as a permanent member of the Canadian International Trade\nTribunal to hold office during good behaviour for a term of five years.\n",
  "registration": "",
  "registration_type": "",
  "registration_id": "",
  "registration_publication_date": ""
}