{
  "html": "<table border=\"1px\" style=\"width: 100%;\"> <tbody><tr><td>&nbsp;</td>\n\t\t\t\t\t<th>PC Number</th>\n\t\t\t\t\t<th>Date</th>\n\t\t\t\t\t<th>Chapter</th>\n\t\t\t\t\t<th>Bill</th>\n\t\t\t\t\t<th>Dept</th></tr><tr><td style=\"min-width: 120px;\">&nbsp;</td><td>1992-2504</td><td>1992-12-03</td><td>0</td><td></td><td>,&nbsp; ND,&nbsp; ,&nbsp; ,&nbsp; </td></tr><tr><td>Precis</td><td colspan=\"5\" id=\"precis\">Redress of grievance. (Kempling)\n\n</td></tr><tr><td>Attachments</td><td colspan=\"5\"></td></tr></tbody></table>",
  "pcNumber": "1992-2504",
  "htmlHash": "ca3a6b1232326dda7b6e7adb517aa63e",
  "attachments": [],
  "date": "1992-12-03",
  "chapter": "0",
  "bill": "",
  "department": ", ND, , , ",
  "act": "",
  "subject": "",
  "precis": "Redress of grievance. (Kempling)\n\n",
  "registration": "",
  "registration_type": "",
  "registration_id": "",
  "registration_publication_date": ""
}