{
  "html": "<table border=\"1px\" style=\"width: 100%;\"> <tbody><tr><td>&nbsp;</td>\n\t\t\t\t\t<th>PC Number</th>\n\t\t\t\t\t<th>Date</th>\n\t\t\t\t\t<th>Chapter</th>\n\t\t\t\t\t<th>Bill</th>\n\t\t\t\t\t<th>Dept</th></tr><tr><td style=\"min-width: 120px;\">&nbsp;</td><td>1993-0925</td><td>1993-05-05</td><td>0</td><td></td><td>,&nbsp; ,&nbsp; ,&nbsp; ,&nbsp; JUS</td></tr><tr><td>Precis</td><td colspan=\"5\" id=\"precis\">Appointment of Weldon Graser, of Fredericton, New Brunswick, as a Judge of\nThe Court of Queen's Bench of New Brunswick, Family Division, and ex\nofficio a Judge of The Court of Appeal of New Brunswick.\n</td></tr><tr><td>Attachments</td><td colspan=\"5\"></td></tr></tbody></table>",
  "pcNumber": "1993-0925",
  "htmlHash": "22ef8dc03c306c45ab124108692158fd",
  "attachments": [],
  "date": "1993-05-05",
  "chapter": "0",
  "bill": "",
  "department": ", , , , JUS",
  "act": "",
  "subject": "",
  "precis": "Appointment of Weldon Graser, of Fredericton, New Brunswick, as a Judge of\nThe Court of Queen's Bench of New Brunswick, Family Division, and ex\nofficio a Judge of The Court of Appeal of New Brunswick.\n",
  "registration": "",
  "registration_type": "",
  "registration_id": "",
  "registration_publication_date": ""
}