{
  "html": "<table border=\"1px\" style=\"width: 100%;\"> <tbody><tr><td>&nbsp;</td>\n\t\t\t\t\t<th>PC Number</th>\n\t\t\t\t\t<th>Date</th>\n\t\t\t\t\t<th>Chapter</th>\n\t\t\t\t\t<th>Bill</th>\n\t\t\t\t\t<th>Dept</th></tr><tr><td style=\"min-width: 120px;\">&nbsp;</td><td>1995-0530</td><td>1995-03-28</td><td>0</td><td></td><td>RESOURCES,&nbsp; ,&nbsp; ,&nbsp; ,&nbsp; </td></tr><tr><td>Precis</td><td colspan=\"5\" id=\"precis\">Appointment of the Surveyor General as Chairman of the Board of Examiners\nfor Canada Land Surveyors.\n</td></tr><tr><td>Attachments</td><td colspan=\"5\"></td></tr></tbody></table>",
  "pcNumber": "1995-0530",
  "htmlHash": "a2c4399beba6e299da82ef17c379f4c2",
  "attachments": [],
  "date": "1995-03-28",
  "chapter": "0",
  "bill": "",
  "department": "RESOURCES, , , , ",
  "act": "",
  "subject": "",
  "precis": "Appointment of the Surveyor General as Chairman of the Board of Examiners\nfor Canada Land Surveyors.\n",
  "registration": "",
  "registration_type": "",
  "registration_id": "",
  "registration_publication_date": ""
}