{
  "html": "<table border=\"1px\" style=\"width: 100%;\"> <tbody><tr><td>&nbsp;</td>\n\t\t\t\t\t<th>PC Number</th>\n\t\t\t\t\t<th>Date</th>\n\t\t\t\t\t<th>Chapter</th>\n\t\t\t\t\t<th>Bill</th>\n\t\t\t\t\t<th>Dept</th></tr><tr><td style=\"min-width: 120px;\">&nbsp;</td><td>1995-1601</td><td>1995-09-19</td><td>0</td><td></td><td>,&nbsp; ,&nbsp; ,&nbsp; SGC,&nbsp; </td></tr><tr><td>Precis</td><td colspan=\"5\" id=\"precis\">Administrative discharge (retirement) of Assistant Commissioner Jos.\nCharles Antoine Luc Pierre GÉNÉREUX of the Royal Canadian Mounted Police.\n</td></tr><tr><td>Attachments</td><td colspan=\"5\"></td></tr></tbody></table>",
  "pcNumber": "1995-1601",
  "htmlHash": "430fbcb927a24f2d34e92e7edb7e38d7",
  "attachments": [],
  "date": "1995-09-19",
  "chapter": "0",
  "bill": "",
  "department": ", , , SGC, ",
  "act": "",
  "subject": "",
  "precis": "Administrative discharge (retirement) of Assistant Commissioner Jos.\nCharles Antoine Luc Pierre GÉNÉREUX of the Royal Canadian Mounted Police.\n",
  "registration": "",
  "registration_type": "",
  "registration_id": "",
  "registration_publication_date": ""
}