{
  "html": "<table border=\"1px\" style=\"width: 100%;\"> <tbody><tr><td>&nbsp;</td>\n\t\t\t\t\t<th>PC Number</th>\n\t\t\t\t\t<th>Date</th>\n\t\t\t\t\t<th>Chapter</th>\n\t\t\t\t\t<th>Bill</th>\n\t\t\t\t\t<th>Dept</th></tr><tr><td style=\"min-width: 120px;\">&nbsp;</td><td>1997-1977</td><td>1997-12-18</td><td>0</td><td></td><td>,&nbsp; ,&nbsp; ,&nbsp; ,&nbsp; ,&nbsp; ,&nbsp; ,&nbsp; ,&nbsp; ,&nbsp; CAN PORTS,&nbsp; TB,&nbsp; TC,&nbsp; ,&nbsp; ,&nbsp; </td></tr><tr><td>Precis</td><td colspan=\"5\" id=\"precis\">Order (a) approving the Corporate Plan of the ST. JOHN'S PORT CORPORATION\nfor the years 1998 to 2002, and (b) authorizing it to generally do such\nthings as it deems necessary for the efficient management of its business.\n</td></tr><tr><td>Attachments</td><td colspan=\"5\"></td></tr></tbody></table>",
  "pcNumber": "1997-1977",
  "htmlHash": "dec6f854f037505beb68d8bedf0abb0b",
  "attachments": [],
  "date": "1997-12-18",
  "chapter": "0",
  "bill": "",
  "department": ", , , , , , , , , CAN PORTS, TB, TC, , , ",
  "act": "",
  "subject": "",
  "precis": "Order (a) approving the Corporate Plan of the ST. JOHN'S PORT CORPORATION\nfor the years 1998 to 2002, and (b) authorizing it to generally do such\nthings as it deems necessary for the efficient management of its business.\n",
  "registration": "",
  "registration_type": "",
  "registration_id": "",
  "registration_publication_date": ""
}