{
  "html": "<table border=\"1px\" style=\"width: 100%;\"> <tbody><tr><td>&nbsp;</td>\n\t\t\t\t\t<th>PC Number</th>\n\t\t\t\t\t<th>Date</th>\n\t\t\t\t\t<th>Chapter</th>\n\t\t\t\t\t<th>Bill</th>\n\t\t\t\t\t<th>Dept</th></tr><tr><td style=\"min-width: 120px;\">&nbsp;</td><td>1997-1135</td><td>1997-08-27</td><td>0</td><td></td><td>,&nbsp; ,&nbsp; ,&nbsp; JUS,&nbsp; </td></tr><tr><td>Precis</td><td colspan=\"5\" id=\"precis\">Appointment of MARC M. MONNIN, of Winnipeg, Manitoba, as a Judge of Her\nMajesty's Court of Queen's Bench of Manitoba.\n</td></tr><tr><td>Attachments</td><td colspan=\"5\"></td></tr></tbody></table>",
  "pcNumber": "1997-1135",
  "htmlHash": "9c971e3ecb1e42c1a3fcaf78c0db8486",
  "attachments": [],
  "date": "1997-08-27",
  "chapter": "0",
  "bill": "",
  "department": ", , , JUS, ",
  "act": "",
  "subject": "",
  "precis": "Appointment of MARC M. MONNIN, of Winnipeg, Manitoba, as a Judge of Her\nMajesty's Court of Queen's Bench of Manitoba.\n",
  "registration": "",
  "registration_type": "",
  "registration_id": "",
  "registration_publication_date": ""
}