{
  "html": "<table border=\"1px\" style=\"width: 100%;\"> <tbody><tr><td>&nbsp;</td>\n\t\t\t\t\t<th>PC Number</th>\n\t\t\t\t\t<th>Date</th>\n\t\t\t\t\t<th>Chapter</th>\n\t\t\t\t\t<th>Bill</th>\n\t\t\t\t\t<th>Dept</th></tr><tr><td style=\"min-width: 120px;\">&nbsp;</td><td>1997-1399</td><td>1997-09-30</td><td>0</td><td></td><td>INDUSTRY,&nbsp; ,&nbsp; ,&nbsp; ,&nbsp; </td></tr><tr><td>Precis</td><td colspan=\"5\" id=\"precis\">Appointment of KLINVELD PEAT MARWICK GOEDERLER (KPMG), of Toronto,\nOntario, as a joint auditor of the Business Development Bank of Canada\nfor the fiscal year commencing April 1, 1997.\n</td></tr><tr><td>Attachments</td><td colspan=\"5\"></td></tr></tbody></table>",
  "pcNumber": "1997-1399",
  "htmlHash": "ce17b56a60546b1b57a524df9f10ae34",
  "attachments": [],
  "date": "1997-09-30",
  "chapter": "0",
  "bill": "",
  "department": "INDUSTRY, , , , ",
  "act": "",
  "subject": "",
  "precis": "Appointment of KLINVELD PEAT MARWICK GOEDERLER (KPMG), of Toronto,\nOntario, as a joint auditor of the Business Development Bank of Canada\nfor the fiscal year commencing April 1, 1997.\n",
  "registration": "",
  "registration_type": "",
  "registration_id": "",
  "registration_publication_date": ""
}