{
  "html": "<table border=\"1px\" style=\"width: 100%;\"> <tbody><tr><td>&nbsp;</td>\n\t\t\t\t\t<th>PC Number</th>\n\t\t\t\t\t<th>Date</th>\n\t\t\t\t\t<th>Chapter</th>\n\t\t\t\t\t<th>Bill</th>\n\t\t\t\t\t<th>Dept</th></tr><tr><td style=\"min-width: 120px;\">&nbsp;</td><td>1998-1511</td><td>1998-08-26</td><td>0</td><td></td><td>,&nbsp; ,&nbsp; ,&nbsp; ,&nbsp; IA&amp;ND,&nbsp; TB,&nbsp; ,&nbsp; ,&nbsp; ,&nbsp; </td></tr><tr><td>Precis</td><td colspan=\"5\" id=\"precis\">Regulations Amending the CANADA MINING REGULATIONS which eliminate the\nthree-year royalty free period and remove an incentive which favoured\nshort-life high-grade mines over long-life operations.\n</td></tr><tr><td>Registration</td><td colspan=\"5\" id=\"registration\"><strong>Registration: </strong>SOR/ 1998-0433  <strong>Publication Date:</strong> 1998-09-16</td></tr><tr><td>Attachments</td><td colspan=\"5\"></td></tr></tbody></table>",
  "pcNumber": "1998-1511",
  "htmlHash": "9c118c2e676cc20f70cfaad9ce6a0cf7",
  "attachments": [],
  "date": "1998-08-26",
  "chapter": "0",
  "bill": "",
  "department": ", , , , IA&ND, TB, , , , ",
  "act": "",
  "subject": "",
  "precis": "Regulations Amending the CANADA MINING REGULATIONS which eliminate the\nthree-year royalty free period and remove an incentive which favoured\nshort-life high-grade mines over long-life operations.\n",
  "registration": "Registration: SOR/ 1998-0433  Publication Date: 1998-09-16",
  "registration_type": "SOR",
  "registration_id": "1998-0433",
  "registration_publication_date": "1998-09-16"
}