{
  "html": "<table border=\"1px\" style=\"width: 100%;\"> <tbody><tr><td>&nbsp;</td>\n\t\t\t\t\t<th>PC Number</th>\n\t\t\t\t\t<th>Date</th>\n\t\t\t\t\t<th>Chapter</th>\n\t\t\t\t\t<th>Bill</th>\n\t\t\t\t\t<th>Dept</th></tr><tr><td style=\"min-width: 120px;\">&nbsp;</td><td>2000-1669</td><td>2000-10-23</td><td>0</td><td></td><td>,&nbsp; RESOURCES,&nbsp; CWB,&nbsp; ,&nbsp; ,&nbsp; ,&nbsp; </td></tr><tr><td>Precis</td><td colspan=\"5\" id=\"precis\">Authority for THE CANADIAN WHEAT BOARD to make a contribution to the\nUNIVERSITY OF MANITOBA for its Agribusiness Chair in Co-operatives and\nGroup Marketing.\n</td></tr><tr><td>Attachments</td><td colspan=\"5\"></td></tr></tbody></table>",
  "pcNumber": "2000-1669",
  "htmlHash": "9aa40234fd655870efc50a1c5c5aad3a",
  "attachments": [],
  "date": "2000-10-23",
  "chapter": "0",
  "bill": "",
  "department": ", RESOURCES, CWB, , , , ",
  "act": "",
  "subject": "",
  "precis": "Authority for THE CANADIAN WHEAT BOARD to make a contribution to the\nUNIVERSITY OF MANITOBA for its Agribusiness Chair in Co-operatives and\nGroup Marketing.\n",
  "registration": "",
  "registration_type": "",
  "registration_id": "",
  "registration_publication_date": ""
}