{
  "html": "<table border=\"1px\" style=\"width: 100%;\"> <tbody><tr><td>&nbsp;</td>\n\t\t\t\t\t<th>PC Number</th>\n\t\t\t\t\t<th>Date</th>\n\t\t\t\t\t<th>Chapter</th>\n\t\t\t\t\t<th>Bill</th>\n\t\t\t\t\t<th>Dept</th></tr><tr><td style=\"min-width: 120px;\">&nbsp;</td><td>2001-0039</td><td>2001-01-09</td><td>0</td><td></td><td>SGC,&nbsp; ,&nbsp; ,&nbsp; ,&nbsp; </td></tr><tr><td>Precis</td><td colspan=\"5\" id=\"precis\">Promotion of the following OFFICERS of the Royal Canadian Mounted Police:\n.\n    OFFICER                                          NEW RANK\n    -------------------------------------------      --------------------\n.\n 1. Inspector Fraser Gordon MACAULAY                 Superintendent\n 2. Inspector John Douglas NEILY                     Superintendent\n 3. Inspector Albert Roger Joseph ST. MARTIN         Superintendent\n 4. Chief Superintendent Joseph Donat Michel SÉGUIN  Assistant Commissioner\n 5. Chief Superintendent John Robert Franklin SPICE  Assistant Commissioner\n.\n</td></tr><tr><td>Attachments</td><td colspan=\"5\"></td></tr></tbody></table>",
  "pcNumber": "2001-0039",
  "htmlHash": "7aec30c8b435a12ed6f0621f2f58b2ad",
  "attachments": [],
  "date": "2001-01-09",
  "chapter": "0",
  "bill": "",
  "department": "SGC, , , , ",
  "act": "",
  "subject": "",
  "precis": "Promotion of the following OFFICERS of the Royal Canadian Mounted Police:\n.\n    OFFICER                                          NEW RANK\n    -------------------------------------------      --------------------\n.\n 1. Inspector Fraser Gordon MACAULAY                 Superintendent\n 2. Inspector John Douglas NEILY                     Superintendent\n 3. Inspector Albert Roger Joseph ST. MARTIN         Superintendent\n 4. Chief Superintendent Joseph Donat Michel SÉGUIN  Assistant Commissioner\n 5. Chief Superintendent John Robert Franklin SPICE  Assistant Commissioner\n.\n",
  "registration": "",
  "registration_type": "",
  "registration_id": "",
  "registration_publication_date": ""
}