{
  "html": "<table border=\"1px\" style=\"width: 100%;\"> <tbody><tr><td>&nbsp;</td>\n\t\t\t\t\t<th>PC Number</th>\n\t\t\t\t\t<th>Date</th>\n\t\t\t\t\t<th>Chapter</th>\n\t\t\t\t\t<th>Bill</th>\n\t\t\t\t\t<th>Dept</th></tr><tr><td style=\"min-width: 120px;\">&nbsp;</td><td>2002-1127</td><td>2002-06-21</td><td>0</td><td></td><td>,&nbsp; ,&nbsp; FAIT,&nbsp; ,&nbsp; </td></tr><tr><td>Precis</td><td colspan=\"5\" id=\"precis\">Re-appointment of LEONARD M. GOOD of Nepean, Ontario, to be a governor of\nthe Board of Governors of the International Development Research Centre,\nto hold office during pleasure for a term of four years.\n</td></tr><tr><td>Attachments</td><td colspan=\"5\"></td></tr></tbody></table>",
  "pcNumber": "2002-1127",
  "htmlHash": "526f0d49bbd2a4d2e2471f487b944531",
  "attachments": [],
  "date": "2002-06-21",
  "chapter": "0",
  "bill": "",
  "department": ", , FAIT, , ",
  "act": "",
  "subject": "",
  "precis": "Re-appointment of LEONARD M. GOOD of Nepean, Ontario, to be a governor of\nthe Board of Governors of the International Development Research Centre,\nto hold office during pleasure for a term of four years.\n",
  "registration": "",
  "registration_type": "",
  "registration_id": "",
  "registration_publication_date": ""
}