{
  "html": "<table border=\"1px\" style=\"width: 100%;\"> <tbody><tr><td>&nbsp;</td>\n\t\t\t\t\t<th>PC Number</th>\n\t\t\t\t\t<th>Date</th>\n\t\t\t\t\t<th>Chapter</th>\n\t\t\t\t\t<th>Bill</th>\n\t\t\t\t\t<th>Dept</th></tr><tr><td style=\"min-width: 120px;\">&nbsp;</td><td>2002-0184</td><td>2002-02-07</td><td>0</td><td></td><td>,&nbsp; ,&nbsp; PMO,&nbsp; ,&nbsp; </td></tr><tr><td>Precis</td><td colspan=\"5\" id=\"precis\">Enactment of an ORDER AMENDING SCHEDULE I.1 TO THE FINANCIAL ADMINISTRATION\nACT which removes the reference to the APPROPRIATE MINISTER for the\nMILLENNIUM BUREAU OF CANADA, effective March 31, 2002.\n</td></tr><tr><td>Registration</td><td colspan=\"5\" id=\"registration\"><strong>Registration: </strong>SOR/ 2002-0069  <strong>Publication Date:</strong> 2002-02-27</td></tr><tr><td>Attachments</td><td colspan=\"5\"></td></tr></tbody></table>",
  "pcNumber": "2002-0184",
  "htmlHash": "7c4463d6f78ba12e4bbdeed509ff7135",
  "attachments": [],
  "date": "2002-02-07",
  "chapter": "0",
  "bill": "",
  "department": ", , PMO, , ",
  "act": "",
  "subject": "",
  "precis": "Enactment of an ORDER AMENDING SCHEDULE I.1 TO THE FINANCIAL ADMINISTRATION\nACT which removes the reference to the APPROPRIATE MINISTER for the\nMILLENNIUM BUREAU OF CANADA, effective March 31, 2002.\n",
  "registration": "Registration: SOR/ 2002-0069  Publication Date: 2002-02-27",
  "registration_type": "SOR",
  "registration_id": "2002-0069",
  "registration_publication_date": "2002-02-27"
}