{
  "html": "<table border=\"1px\" style=\"width: 100%;\"> <tbody><tr><td>&nbsp;</td>\n\t\t\t\t\t<th>PC Number</th>\n\t\t\t\t\t<th>Date</th>\n\t\t\t\t\t<th>Chapter</th>\n\t\t\t\t\t<th>Bill</th>\n\t\t\t\t\t<th>Dept</th></tr><tr><td style=\"min-width: 120px;\">&nbsp;</td><td>2007-0799</td><td>2007-05-15</td><td></td><td></td><td>PMO,&nbsp; EC,&nbsp; ,&nbsp; ,&nbsp; ,&nbsp; ,&nbsp; ,&nbsp; ,&nbsp; </td></tr><tr><td>Act</td><td colspan=\"5\">Parks Canada Agency Act</td></tr><tr><td>Precis</td><td colspan=\"5\" id=\"precis\">Reappointment of ALAN LATOURELLE, of Ottawa, Ontario, to be Chief Executive Officer of the Parks Canada Agency, to hold office during pleasure for a term of five years, effective August 7, 2007.</td></tr><tr><td>Attachments</td><td colspan=\"5\"><a href=\"attachment.php?attach=16481&amp;lang=en\">Attachment</a></td></tr></tbody></table>",
  "pcNumber": "2007-0799",
  "htmlHash": "fb55d487bc011ff988d53dc2403d1a2c",
  "attachments": [
    "16481"
  ],
  "date": "2007-05-15",
  "chapter": "",
  "bill": "",
  "department": "PMO, EC, , , , , , , ",
  "act": "Parks Canada Agency Act",
  "subject": "",
  "precis": "Reappointment of ALAN LATOURELLE, of Ottawa, Ontario, to be Chief Executive Officer of the Parks Canada Agency, to hold office during pleasure for a term of five years, effective August 7, 2007.",
  "registration": "",
  "registration_type": "",
  "registration_id": "",
  "registration_publication_date": ""
}