{
  "html": "<table border=\"1px\" style=\"width: 100%;\"> <tbody><tr><td>&nbsp;</td>\n\t\t\t\t\t<th>PC Number</th>\n\t\t\t\t\t<th>Date</th>\n\t\t\t\t\t<th>Chapter</th>\n\t\t\t\t\t<th>Bill</th>\n\t\t\t\t\t<th>Dept</th></tr><tr><td style=\"min-width: 120px;\">&nbsp;</td><td>2008-1317</td><td>2008-07-04</td><td></td><td></td><td>,&nbsp; ,&nbsp; HRSD,&nbsp; ,&nbsp; ,&nbsp; </td></tr><tr><td>Act</td><td colspan=\"5\">Wage Earner Protection Program Act</td></tr><tr><td>Precis</td><td colspan=\"5\" id=\"precis\">Wage Earner Protection Program Regulations, establishing procedural details in 11 subject areas under the Act, ranging from a definition of “wages” to the fees payable to insolvency professionals for duties performed under the Act.</td></tr><tr><td>Registration</td><td colspan=\"5\" id=\"registration\"><strong>Registration: </strong>SOR/ 2008-0222  <strong>Publication Date:</strong> 2008-07-23</td></tr><tr><td>Attachments</td><td colspan=\"5\"><a href=\"attachment.php?attach=19165&amp;lang=en\">Attachment</a></td></tr></tbody></table>",
  "pcNumber": "2008-1317",
  "htmlHash": "fb6789a06843a7f8029433d9abd5c536",
  "attachments": [
    "19165"
  ],
  "date": "2008-07-04",
  "chapter": "",
  "bill": "",
  "department": ", , HRSD, , , ",
  "act": "Wage Earner Protection Program Act",
  "subject": "",
  "precis": "Wage Earner Protection Program Regulations, establishing procedural details in 11 subject areas under the Act, ranging from a definition of “wages” to the fees payable to insolvency professionals for duties performed under the Act.",
  "registration": "Registration: SOR/ 2008-0222  Publication Date: 2008-07-23",
  "registration_type": "SOR",
  "registration_id": "2008-0222",
  "registration_publication_date": "2008-07-23"
}