{
  "html": "<table border=\"1px\" style=\"width: 100%;\"> <tbody><tr><td>&nbsp;</td>\n\t\t\t\t\t<th>PC Number</th>\n\t\t\t\t\t<th>Date</th>\n\t\t\t\t\t<th>Chapter</th>\n\t\t\t\t\t<th>Bill</th>\n\t\t\t\t\t<th>Dept</th></tr><tr><td style=\"min-width: 120px;\">&nbsp;</td><td>2009-0732</td><td>2009-05-14</td><td></td><td></td><td>RESOURCES,&nbsp; ,&nbsp; ,&nbsp; ,&nbsp; </td></tr><tr><td>Act</td><td colspan=\"5\">National Energy Board Act</td></tr><tr><td>Precis</td><td colspan=\"5\" id=\"precis\">Re-appointment of KENNETH R.W. VOLLMAN of Calgary, Alberta, as a part-time member of the National Energy Board, to hold office during pleasure for a term ending December 31, 2010, effective June 27, 2009.</td></tr><tr><td>Attachments</td><td colspan=\"5\"><a href=\"attachment.php?attach=20613&amp;lang=en\">Attachment</a></td></tr></tbody></table>",
  "pcNumber": "2009-0732",
  "htmlHash": "48f7759b6ed7ea2ca91aedbfa704f651",
  "attachments": [
    "20613"
  ],
  "date": "2009-05-14",
  "chapter": "",
  "bill": "",
  "department": "RESOURCES, , , , ",
  "act": "National Energy Board Act",
  "subject": "",
  "precis": "Re-appointment of KENNETH R.W. VOLLMAN of Calgary, Alberta, as a part-time member of the National Energy Board, to hold office during pleasure for a term ending December 31, 2010, effective June 27, 2009.",
  "registration": "",
  "registration_type": "",
  "registration_id": "",
  "registration_publication_date": ""
}