{
  "html": "<table border=\"1px\" style=\"width: 100%;\"> <tbody><tr><td>&nbsp;</td>\n\t\t\t\t\t<th>PC Number</th>\n\t\t\t\t\t<th>Date</th>\n\t\t\t\t\t<th>Chapter</th>\n\t\t\t\t\t<th>Bill</th>\n\t\t\t\t\t<th>Dept</th></tr><tr><td style=\"min-width: 120px;\">&nbsp;</td><td>2010-0243</td><td>2010-03-08</td><td></td><td></td><td>HERITAGE,&nbsp; ,&nbsp; ,&nbsp; ,&nbsp; </td></tr><tr><td>Act</td><td colspan=\"5\">Telefilm Canada Act</td></tr><tr><td>Precis</td><td colspan=\"5\" id=\"precis\">Appointment of CAROLLE BRABANT of Montreal, Quebec, as Executive Director of Telefilm Canada, to hold office during pleasure for a term of three years, effective March 15, 2010.</td></tr><tr><td>Attachments</td><td colspan=\"5\"><a href=\"attachment.php?attach=22214&amp;lang=en\">Attachment</a></td></tr></tbody></table>",
  "pcNumber": "2010-0243",
  "htmlHash": "dec86487e22d651aebf4908bbb63c623",
  "attachments": [
    "22214"
  ],
  "date": "2010-03-08",
  "chapter": "",
  "bill": "",
  "department": "HERITAGE, , , , ",
  "act": "Telefilm Canada Act",
  "subject": "",
  "precis": "Appointment of CAROLLE BRABANT of Montreal, Quebec, as Executive Director of Telefilm Canada, to hold office during pleasure for a term of three years, effective March 15, 2010.",
  "registration": "",
  "registration_type": "",
  "registration_id": "",
  "registration_publication_date": ""
}