{
  "html": "<table border=\"1px\" style=\"width: 100%;\"> <tbody><tr><td>&nbsp;</td>\n\t\t\t\t\t<th>PC Number</th>\n\t\t\t\t\t<th>Date</th>\n\t\t\t\t\t<th>Chapter</th>\n\t\t\t\t\t<th>Bill</th>\n\t\t\t\t\t<th>Dept</th></tr><tr><td style=\"min-width: 120px;\">&nbsp;</td><td>2012-0080</td><td>2012-02-14</td><td></td><td></td><td>HC,&nbsp; ,&nbsp; ,&nbsp; ,&nbsp; </td></tr><tr><td>Act</td><td colspan=\"5\">Assisted Human Reproduction Act</td></tr><tr><td>Precis</td><td colspan=\"5\" id=\"precis\">Reappointment of ELINOR WILSON of Vancouver, British Columbia, as President of the Assisted Human Reproduction Agency of Canada to hold office during pleasure for a term ending September 30, 2012, effective February 14, 2012.</td></tr><tr><td>Attachments</td><td colspan=\"5\"><a href=\"attachment.php?attach=25502&amp;lang=en\">Attachment</a></td></tr></tbody></table>",
  "pcNumber": "2012-0080",
  "htmlHash": "83fb58206b58420fe0bea56b075c004b",
  "attachments": [
    "25502"
  ],
  "date": "2012-02-14",
  "chapter": "",
  "bill": "",
  "department": "HC, , , , ",
  "act": "Assisted Human Reproduction Act",
  "subject": "",
  "precis": "Reappointment of ELINOR WILSON of Vancouver, British Columbia, as President of the Assisted Human Reproduction Agency of Canada to hold office during pleasure for a term ending September 30, 2012, effective February 14, 2012.",
  "registration": "",
  "registration_type": "",
  "registration_id": "",
  "registration_publication_date": ""
}