{
  "html": "<table border=\"1px\" style=\"width: 100%;\"> <tbody><tr><td>&nbsp;</td>\n\t\t\t\t\t<th>PC Number</th>\n\t\t\t\t\t<th>Date</th>\n\t\t\t\t\t<th>Chapter</th>\n\t\t\t\t\t<th>Bill</th>\n\t\t\t\t\t<th>Dept</th></tr><tr><td style=\"min-width: 120px;\">&nbsp;</td><td>2013-0908</td><td>2013-08-29</td><td></td><td></td><td>,&nbsp; FIN,&nbsp; ,&nbsp; ,&nbsp; </td></tr><tr><td>Act</td><td colspan=\"5\">Financial Consumer Agency of  Canada Act</td></tr><tr><td>Precis</td><td colspan=\"5\" id=\"precis\">Appointment of LUCIE TEDESCO of Greely, Ontario, as Commissioner of the Financial Consumer Agency of Canada to hold office during good behaviour for a term of five years, effective September 3, 2013.</td></tr><tr><td>Attachments</td><td colspan=\"5\"><a href=\"attachment.php?attach=28164&amp;lang=en\">Attachment</a></td></tr></tbody></table>",
  "pcNumber": "2013-0908",
  "htmlHash": "2cd29ab0a7f6d4e1fc12b8ca7fcdb538",
  "attachments": [
    "28164"
  ],
  "date": "2013-08-29",
  "chapter": "",
  "bill": "",
  "department": ", FIN, , , ",
  "act": "Financial Consumer Agency of  Canada Act",
  "subject": "",
  "precis": "Appointment of LUCIE TEDESCO of Greely, Ontario, as Commissioner of the Financial Consumer Agency of Canada to hold office during good behaviour for a term of five years, effective September 3, 2013.",
  "registration": "",
  "registration_type": "",
  "registration_id": "",
  "registration_publication_date": ""
}