{
  "html": "<table border=\"1px\" style=\"width: 100%;\"> <tbody><tr><td>&nbsp;</td>\n\t\t\t\t\t<th>PC Number</th>\n\t\t\t\t\t<th>Date</th>\n\t\t\t\t\t<th>Chapter</th>\n\t\t\t\t\t<th>Bill</th>\n\t\t\t\t\t<th>Dept</th></tr><tr><td style=\"min-width: 120px;\">&nbsp;</td><td>2019-0894</td><td>2019-06-22</td><td></td><td></td><td>JUS,&nbsp; ,&nbsp; ,&nbsp; ,&nbsp; </td></tr><tr><td>Act</td><td colspan=\"5\">Other Than Statutory Authority</td></tr><tr><td>Precis</td><td colspan=\"5\" id=\"precis\">Appointment of the HONOURABLE BENOÎT MOORE, a puisne Judge of the Superior Court of Quebec for the district of Montréal, to be a puisne Judge of the Court of Appeal of Quebec.</td></tr><tr><td>Attachments</td><td colspan=\"5\"><a href=\"attachment.php?attach=38219&amp;lang=en\">Attachment</a></td></tr></tbody></table>",
  "pcNumber": "2019-0894",
  "htmlHash": "a92887d7bd1a664a8ddba2f52cb2a41a",
  "attachments": [
    "38219"
  ],
  "date": "2019-06-22",
  "chapter": "",
  "bill": "",
  "department": "JUS, , , , ",
  "act": "Other Than Statutory Authority",
  "subject": "",
  "precis": "Appointment of the HONOURABLE BENOÎT MOORE, a puisne Judge of the Superior Court of Quebec for the district of Montréal, to be a puisne Judge of the Court of Appeal of Quebec.",
  "registration": "",
  "registration_type": "",
  "registration_id": "",
  "registration_publication_date": ""
}