{
  "html": "<table border=\"1px\" style=\"width: 100%;\"> <tbody><tr><td>&nbsp;</td>\n\t\t\t\t\t<th>PC Number</th>\n\t\t\t\t\t<th>Date</th>\n\t\t\t\t\t<th>Chapter</th>\n\t\t\t\t\t<th>Bill</th>\n\t\t\t\t\t<th>Dept</th></tr><tr><td style=\"min-width: 120px;\">&nbsp;</td><td>2020-0285</td><td>2020-04-28</td><td></td><td></td><td>ISED,&nbsp; ,&nbsp; ,&nbsp; ,&nbsp; </td></tr><tr><td>Act</td><td colspan=\"5\">Natural Sciences and Engineering Research Council Act</td></tr><tr><td>Precis</td><td colspan=\"5\" id=\"precis\">Re-appointment of HELGE SEETZEN of Westmount, Quebec, as a member of the Natural Sciences and Engineering Research Council, to hold office during pleasure for a term of two years.</td></tr><tr><td>Attachments</td><td colspan=\"5\"><a href=\"attachment.php?attach=39195&amp;lang=en\">Attachment</a></td></tr></tbody></table>",
  "pcNumber": "2020-0285",
  "htmlHash": "026b94960e9048529432ba35c4c0fb40",
  "attachments": [
    "39195"
  ],
  "date": "2020-04-28",
  "chapter": "",
  "bill": "",
  "department": "ISED, , , , ",
  "act": "Natural Sciences and Engineering Research Council Act",
  "subject": "",
  "precis": "Re-appointment of HELGE SEETZEN of Westmount, Quebec, as a member of the Natural Sciences and Engineering Research Council, to hold office during pleasure for a term of two years.",
  "registration": "",
  "registration_type": "",
  "registration_id": "",
  "registration_publication_date": ""
}