{
  "html": "<table border=\"1px\" style=\"width: 100%;\"> <tbody><tr><td>&nbsp;</td>\n\t\t\t\t\t<th>PC Number</th>\n\t\t\t\t\t<th>Date</th>\n\t\t\t\t\t<th>Chapter</th>\n\t\t\t\t\t<th>Bill</th>\n\t\t\t\t\t<th>Dept</th></tr><tr><td style=\"min-width: 120px;\">&nbsp;</td><td>2020-0266</td><td>2020-04-22</td><td></td><td></td><td>AAFC,&nbsp; ,&nbsp; ,&nbsp; ,&nbsp; ,&nbsp; ,&nbsp; ,&nbsp; ,&nbsp; </td></tr><tr><td>Act</td><td colspan=\"5\">Farm Credit Canada Act</td></tr><tr><td>Precis</td><td colspan=\"5\" id=\"precis\">Appointment of JANE HALFORD of Edmonton, Alberta, to be Chairperson of the Board of Directors of Farm Credit Canada, to hold office during pleasure for a term of four years.</td></tr><tr><td>Attachments</td><td colspan=\"5\"><a href=\"attachment.php?attach=39174&amp;lang=en\">Attachment</a></td></tr></tbody></table>",
  "pcNumber": "2020-0266",
  "htmlHash": "087279c581b165db14956ecfe642cae2",
  "attachments": [
    "39174"
  ],
  "date": "2020-04-22",
  "chapter": "",
  "bill": "",
  "department": "AAFC, , , , , , , , ",
  "act": "Farm Credit Canada Act",
  "subject": "",
  "precis": "Appointment of JANE HALFORD of Edmonton, Alberta, to be Chairperson of the Board of Directors of Farm Credit Canada, to hold office during pleasure for a term of four years.",
  "registration": "",
  "registration_type": "",
  "registration_id": "",
  "registration_publication_date": ""
}